{"/_error":"pages/_error.js","/_document":"pages/_document.js","/_app":"pages/_app.js","/api/hello":"pages/api/hello.js","/history":"pages/history.html","/dashboard":"pages/dashboard.html","/profile":"pages/profile.html","/":"pages/index.html","/selectedWorkout":"pages/selectedWorkout.html","/login":"pages/login.html","/splash":"pages/splash.html","/workout-finished":"pages/workout-finished.html","/settings":"pages/settings.html","/workout-monitor":"pages/workout-monitor.html","/workouts":"pages/workouts.html","/signup":"pages/signup.html","/404":"pages/404.html"}